[{"aera_id":6,"aera_step2":"Bugis","latitude":1.299966,"longitude":103.8552892},
{"aera_id":6,"aera_step2":"Victoria Street","latitude":1.305772,"longitude":103.8611522},
{"aera_id":6,"aera_step2":"Rochor","latitude":1.3039183,"longitude":103.8527885},
{"aera_id":6,"aera_step2":"Cavenagh Road","latitude":1.3008679,"longitude":103.8431417},
{"aera_id":6,"aera_step2":"Scotts Road","latitude":1.3119944,"longitude":103.837473},
{"aera_id":6,"aera_step2":"Newton","latitude":1.3131833,"longitude":103.8380402},
{"aera_id":6,"aera_step2":"Central Fire Station","latitude":1.2921432,"longitude":103.8487245},
{"aera_id":6,"aera_step2":"Hill Street","latitude":1.2909524,"longitude":103.848755},
{"aera_id":6,"aera_step2":"Chinatown","latitude":1.2829435,"longitude":103.8441517},
{"aera_id":6,"aera_step2":"Depot Road","latitude":1.2818217,"longitude":103.8094157},
{"aera_id":6,"aera_step2":"Habourfront","latitude":1.26491,"longitude":103.82138},
{"aera_id":6,"aera_step2":"Telok Blangah","latitude":1.2829435,"longitude":103.8441517},
{"aera_id":6,"aera_step2":"Kampong Glam","latitude":1.3027922,"longitude":103.8635783},
{"aera_id":6,"aera_step2":"Beach Road","latitude":1.3014905,"longitude":103.8623772},
{"aera_id":6,"aera_step2":"Lavender","latitude":1.3073496,"longitude":103.8631527},
{"aera_id":6,"aera_step2":"Jalan Besar","latitude":1.3106732,"longitude":103.8587351},
{"aera_id":6,"aera_step2":"Little India","latitude":1.3068427,"longitude":103.8492736},
{"aera_id":6,"aera_step2":"Marina South","latitude":1.277063,"longitude":103.8682347},
{"aera_id":6,"aera_step2":"Marina","latitude":1.2889066,"longitude":103.8580825},
{"aera_id":6,"aera_step2":"Esplanade","latitude":1.2934873,"longitude":103.8553908},
{"aera_id":6,"aera_step2":"Suntec","latitude":1.2942651,"longitude":103.8591876},
{"aera_id":6,"aera_step2":"Orchard Road","latitude":1.3012785,"longitude":103.8389486},
{"aera_id":6,"aera_step2":"Outram Road","latitude":1.2845059,"longitude":103.8351582},
{"aera_id":6,"aera_step2":"Tiong Bahru","latitude":1.2861792,"longitude":103.8272252},
{"aera_id":6,"aera_step2":"Prince Edward","latitude":1.307299,"longitude":103.7813889},
{"aera_id":6,"aera_step2":"Anson Road","latitude":1.2758152,"longitude":103.8464915},
{"aera_id":6,"aera_step2":"Queenstown","latitude":1.286898,"longitude":103.712104},
{"aera_id":6,"aera_step2":"Commonwealth","latitude":1.2946226,"longitude":103.8060366},
{"aera_id":6,"aera_step2":"Raffles Place","latitude":1.2835417,"longitude":103.8514602},
{"aera_id":6,"aera_step2":"Redhill","latitude":1.2896482,"longitude":103.8167677},
{"aera_id":6,"aera_step2":"Bukit Merah","latitude":1.2704395,"longitude":103.8283184},
{"aera_id":6,"aera_step2":"Alexandra","latitude":1.277477,"longitude":103.8018803},
{"aera_id":6,"aera_step2":"Robinson Road","latitude":1.2785002,"longitude":103.8486161},
{"aera_id":6,"aera_step2":"Shenton Way","latitude":1.2786955,"longitude":103.8493414},
{"aera_id":6,"aera_step2":"Tanglin Road","latitude":1.3004419,"longitude":103.8176002},
{"aera_id":6,"aera_step2":"River Valley","latitude":1.2976832,"longitude":103.834188},
{"aera_id":6,"aera_step2":"Tanjong Pagar","latitude":1.2766057,"longitude":103.8457793},
{"aera_id":6,"aera_step2":"Bedok Reservoir","latitude":1.3425058,"longitude":103.9252298},
{"aera_id":6,"aera_step2":"Bedok","latitude":1.3239765,"longitude":103.930216},
{"aera_id":6,"aera_step2":"Chai Chee","latitude":1.3254977,"longitude":103.9230158},
{"aera_id":6,"aera_step2":"Changi Airport","latitude":1.3575573,"longitude":103.9884703},
{"aera_id":6,"aera_step2":"Changi Coast","latitude":1.3353876,"longitude":104.0082593},
{"aera_id":6,"aera_step2":"Kallang","latitude":1.310759,"longitude":103.866262},
{"aera_id":6,"aera_step2":"Aljunied","latitude":1.3164515,"longitude":103.8829087},
{"aera_id":6,"aera_step2":"Geylang","latitude":1.3181862,"longitude":103.8870563},
{"aera_id":6,"aera_step2":"Katong","latitude":1.3016238,"longitude":103.9045983},
{"aera_id":6,"aera_step2":"Joo Chiat","latitude":1.3112738,"longitude":103.9011218},
{"aera_id":6,"aera_step2":"Katong","latitude":1.3016238,"longitude":103.9045983},
{"aera_id":6,"aera_step2":"Tanjong Rhu","latitude":1.2982609,"longitude":103.8735555},
{"aera_id":6,"aera_step2":"Kembangan","latitude":1.3210321,"longitude":103.9129269},
{"aera_id":6,"aera_step2":"Loyang","latitude":1.3753678,"longitude":103.9772924},
{"aera_id":6,"aera_step2":"Marine Parade","latitude":1.3026889,"longitude":103.9073952},
{"aera_id":6,"aera_step2":"Pasir Ris","latitude":1.3730307,"longitude":103.949255},
{"aera_id":6,"aera_step2":"Paya Lebar","latitude":1.3174795,"longitude":103.8923525},
{"aera_id":6,"aera_step2":"Geylang Serai","latitude":1.316273,"longitude":103.8975689},
{"aera_id":6,"aera_step2":"Siglap","latitude":1.3126329,"longitude":103.9278453},
{"aera_id":6,"aera_step2":"Singapore Expo","latitude":1.3352329,"longitude":103.9598931},
{"aera_id":6,"aera_step2":"Old Bedok Road","latitude":1.311986,"longitude":103.922546},
{"aera_id":6,"aera_step2":"Changi South","latitude":1.3289284,"longitude":103.9617098},
{"aera_id":6,"aera_step2":"Stadium","latitude":1.3028396,"longitude":103.8753794},
{"aera_id":6,"aera_step2":"Tampines","latitude":1.3546528,"longitude":103.9435712},
{"aera_id":6,"aera_step2":"Simei","latitude":1.3431881,"longitude":103.953371},
{"aera_id":6,"aera_step2":"Bukit Panjang","latitude":1.3779175,"longitude":103.7630947},
{"aera_id":6,"aera_step2":"Bukit Timah Hill","latitude":1.3546901,"longitude":103.7763724},
{"aera_id":6,"aera_step2":"Bukit Timah, King Albert Park","latitude":1.3357025,"longitude":103.7835912},
{"aera_id":6,"aera_step2":"Bukit Timah, Turf Club","latitude":1.337637,"longitude":103.7974744},
{"aera_id":6,"aera_step2":"Stevens Road","latitude":1.3166148,"longitude":103.8258954},
{"aera_id":6,"aera_step2":"Mandai","latitude":1.4235346,"longitude":103.8033499},
{"aera_id":6,"aera_step2":"Sungei Kadut","latitude":1.4149971,"longitude":103.7533106},
{"aera_id":6,"aera_step2":"Neo Tiew","latitude":1.4363815,"longitude":103.7263579},
{"aera_id":6,"aera_step2":"Kranji","latitude":1.4252189,"longitude":103.7619891},
{"aera_id":6,"aera_step2":"Sembawang","latitude":1.4490928,"longitude":103.8200555},
{"aera_id":6,"aera_step2":"Thomson Road","latitude":1.3271261,"longitude":103.8413274},
{"aera_id":6,"aera_step2":"Woodlands","latitude":1.436897,"longitude":103.786216},
{"aera_id":6,"aera_step2":"Marsiling","latitude":1.4325704,"longitude":103.7741243},
{"aera_id":6,"aera_step2":"Amiralty","latitude":1.44128,"longitude":103.80099},
{"aera_id":6,"aera_step2":"Yew Tee","latitude":1.3974608,"longitude":103.7474009},
{"aera_id":6,"aera_step2":"Choa Chu Kang","latitude":1.3853167,"longitude":103.744325},
{"aera_id":6,"aera_step2":"Yishun","latitude":1.4293839,"longitude":103.8350282},
{"aera_id":6,"aera_step2":"Khatib","latitude":1.4173597,"longitude":103.8330179},
{"aera_id":6,"aera_step2":"Ang Mo Kio","latitude":1.3700803,"longitude":103.8495228},
{"aera_id":6,"aera_step2":"Balestier","latitude":1.326226,"longitude":103.8473149},
{"aera_id":6,"aera_step2":"Bendemeer","latitude":1.3173365,"longitude":103.8621293},
{"aera_id":6,"aera_step2":"Bishan","latitude":1.3509859,"longitude":103.8482551},
{"aera_id":6,"aera_step2":"Thomson Road","latitude":1.3271261,"longitude":103.8413274},
{"aera_id":6,"aera_step2":"Braddell","latitude":1.3400707,"longitude":103.8467584},
{"aera_id":6,"aera_step2":"Toa Payoh","latitude":1.3353906,"longitude":103.8497414},
{"aera_id":6,"aera_step2":"Geylang Bahru","latitude":1.3237493,"longitude":103.8695213},
{"aera_id":6,"aera_step2":"Hougang","latitude":1.3708011,"longitude":103.8925443},
{"aera_id":6,"aera_step2":"Serangoon","latitude":1.3497611,"longitude":103.8736841},
{"aera_id":6,"aera_step2":"Yio Chu Kang","latitude":1.3817905,"longitude":103.8449359},
{"aera_id":6,"aera_step2":"Kovan","latitude":1.3601757,"longitude":103.885112},
{"aera_id":6,"aera_step2":"MacPherson Road","latitude":1.3322241,"longitude":103.8832853},
{"aera_id":6,"aera_step2":"Nee Soon","latitude":1.4263793,"longitude":103.8335834},
{"aera_id":6,"aera_step2":"Novena","latitude":1.3205257,"longitude":103.8438813},
{"aera_id":6,"aera_step2":"Paya Lebar (old) Airport","latitude":1.36083,"longitude":103.90944},
{"aera_id":6,"aera_step2":"Punggol","latitude":1.4051973,"longitude":103.9023498},
{"aera_id":6,"aera_step2":"Seletar","latitude":1.4098488,"longitude":103.8773789},
{"aera_id":6,"aera_step2":"Sengkang","latitude":1.3919236,"longitude":103.8954909},
{"aera_id":6,"aera_step2":"Buangkok","latitude":1.382996,"longitude":103.8930569},
{"aera_id":6,"aera_step2":"Serangoon Central","latitude":1.3535142,"longitude":103.8716164},
{"aera_id":6,"aera_step2":"Serangoon Gardens","latitude":1.3624579,"longitude":103.8660127},
{"aera_id":6,"aera_step2":"Woodleigh","latitude":1.3391943,"longitude":103.8708215},
{"aera_id":6,"aera_step2":"Potong Pasir","latitude":1.3314141,"longitude":103.8691381},
{"aera_id":6,"aera_step2":"Macpherson","latitude":1.3262069,"longitude":103.889507},
{"aera_id":6,"aera_step2":"Yio Chu Kang","latitude":1.3817905,"longitude":103.8449359},
{"aera_id":6,"aera_step2":"Bukit Batok","latitude":1.3490572,"longitude":103.7495906},
{"aera_id":6,"aera_step2":"Bukit Gombak","latitude":1.3588929,"longitude":103.7518249},
{"aera_id":6,"aera_step2":"Bukit Timah","latitude":1.3546901,"longitude":103.7763724},
{"aera_id":6,"aera_step2":"Farrer Road","latitude":1.3174812,"longitude":103.8075626},
{"aera_id":6,"aera_step2":"Coronation Road","latitude":1.3226686,"longitude":103.8045968},
{"aera_id":6,"aera_step2":"Clementi","latitude":1.3151003,"longitude":103.7652311},
{"aera_id":6,"aera_step2":"Dover","latitude":1.3113893,"longitude":103.778605},
{"aera_id":6,"aera_step2":"Buona Vista","latitude":1.3066096,"longitude":103.790751},
{"aera_id":6,"aera_step2":"Singapore Polytechnic","latitude":1.309137,"longitude":103.7781437},
{"aera_id":6,"aera_step2":"Hillview","latitude":1.3624042,"longitude":103.7674273},
{"aera_id":6,"aera_step2":"Holland Road","latitude":1.3093567,"longitude":103.8080238},
{"aera_id":6,"aera_step2":"Ghim Moh","latitude":1.310558,"longitude":103.7893244},
{"aera_id":6,"aera_step2":"Jurong East","latitude":1.333108,"longitude":103.7422939},
{"aera_id":6,"aera_step2":"Jurong West","latitude":1.3434392,"longitude":103.7058663},
{"aera_id":6,"aera_step2":"Lakeside","latitude":1.34425,"longitude":103.7206931},
{"aera_id":6,"aera_step2":"Boon Lay","latitude":1.3385504,"longitude":103.7058124},
{"aera_id":6,"aera_step2":"Jurong","latitude":1.33417,"longitude":103.72278},
{"aera_id":6,"aera_step2":"Joo Koon","latitude":1.327735,"longitude":103.6782221},
{"aera_id":6,"aera_step2":"Jurong","latitude":1.33417,"longitude":103.72278},
{"aera_id":6,"aera_step2":"Tuas","latitude":1.3293722,"longitude":103.6482364},
{"aera_id":6,"aera_step2":"Lim Chu Kang","latitude":1.4342172,"longitude":103.7149872},
{"aera_id":6,"aera_step2":"Pasir Panjang","latitude":1.2762014,"longitude":103.7914758},
{"aera_id":6,"aera_step2":"Alexandra","latitude":1.277477,"longitude":103.8018803},
{"aera_id":6,"aera_step2":"Kent Ridge","latitude":1.2933374,"longitude":103.7844936},
{"aera_id":6,"aera_step2":"Taman Jurong","latitude":1.334224,"longitude":103.7226081},
{"aera_id":6,"aera_step2":"Tengah","latitude":1.3655284,"longitude":103.7307585}]